setup.py
machine/__init__.py
machine/timer.py
micropython_machine.egg-info/PKG-INFO
micropython_machine.egg-info/SOURCES.txt
micropython_machine.egg-info/dependency_links.txt
micropython_machine.egg-info/requires.txt
micropython_machine.egg-info/top_level.txt